README.md
setup.py
MainModeling_pkg/MainModeling.py
MainModeling_pkg/__init__.py
MainModeling_pkg.egg-info/PKG-INFO
MainModeling_pkg.egg-info/SOURCES.txt
MainModeling_pkg.egg-info/dependency_links.txt
MainModeling_pkg.egg-info/top_level.txt