Metadata-Version: 2.1
Name: MainModeling-pkg
Version: 0.0.1
Summary: Structural Analysis and Soft Computing
Home-page: https://http://www.diseniosm.com/
Author: Edgar David Mora Martinez
Author-email: edgar.mora@diseniosm.com
License: UNKNOWN
Platform: UNKNOWN
Classifier: Development Status :: 4 - Beta
Classifier: Programming Language :: Python :: 3
Classifier: License :: OSI Approved :: GNU Affero General Public License v3 or later (AGPLv3+)
Classifier: Operating System :: OS Independent
